tmsh.py
tmsh-0.0.5.dist-info/licenses/LICENSE
tmsh-0.0.5.dist-info/METADATA
tmsh-0.0.5.dist-info/WHEEL
tmsh-0.0.5.dist-info/top_level.txt
tmsh-0.0.5.dist-info/RECORD
