Metadata-Version: 2.4
Name: tmsh
Version: 0.0.5
Summary: Type-annotated and linted Python interface for Gmsh
Project-URL: Repository, https://github.com/rupt/tmsh
Classifier: Development Status :: 1 - Planning
Classifier: Operating System :: MacOS :: MacOS X
Classifier: Operating System :: Microsoft :: Windows
Classifier: Operating System :: POSIX :: Linux
Classifier: Programming Language :: Python :: 3 :: Only
Classifier: Programming Language :: Python :: 3.12
Classifier: Programming Language :: Python :: 3.13
Classifier: Programming Language :: Python
Requires-Python: >=3.12
License-File: LICENSE
Requires-Dist: gmsh==4.13.1
Requires-Dist: numpy>=2.0.0
Dynamic: license-file
